IO.py
__init__.py
dbg.py
robotwindow.py
robotworld.py
robotcz-0.0.3.dist-info/METADATA
robotcz-0.0.3.dist-info/WHEEL
robotcz-0.0.3.dist-info/RECORD
